swisper_studio_sdk/__init__.py
swisper_studio_sdk/tracing/__init__.py
swisper_studio_sdk/tracing/client.py
swisper_studio_sdk/tracing/context.py
swisper_studio_sdk/tracing/decorator.py
swisper_studio_sdk/tracing/graph_wrapper.py
swisper_studio_sdk/tracing/redis_publisher.py
swisper_studio_sdk/tracing/tool_observer.py
swisper_studio_sdk/wrappers/__init__.py
swisper_studio_sdk/wrappers/llm_wrapper.py
swisper_studio_sdk/wrappers/tool_wrapper.py
swisper_studio_sdk-0.5.4.dist-info/METADATA
swisper_studio_sdk-0.5.4.dist-info/WHEEL
swisper_studio_sdk-0.5.4.dist-info/top_level.txt
swisper_studio_sdk-0.5.4.dist-info/RECORD
