Metadata-Version: 2.4
Name: swisper-studio-sdk
Version: 0.5.4
Summary: SwisperStudio SDK - Tracing integration for Swisper (internal use)
Author: Fintama SwisperStudio Team
License: Proprietary - Fintama Internal Use Only
Project-URL: Homepage, https://github.com/Fintama/swisper_studio
Project-URL: Repository, https://github.com/Fintama/swisper_studio
Project-URL: Documentation, https://github.com/Fintama/swisper_studio/tree/main/sdk
Requires-Python: >=3.11
Requires-Dist: httpx>=0.25.2
Requires-Dist: langgraph<2.0.0,>=1.0.0
Requires-Dist: langgraph-checkpoint>=2.1.0
Requires-Dist: redis>=5.0.0
Provides-Extra: dev
Requires-Dist: pytest>=7.4.3; extra == "dev"
Requires-Dist: pytest-asyncio>=0.21.1; extra == "dev"
